flet_geolocator/__init__.py
flet_geolocator/geolocator.py
flet_geolocator/types.py
flet_geolocator-0.80.5.dist-info/licenses/LICENSE
flutter/flet_geolocator/analysis_options.yaml
flutter/flet_geolocator/pubspec.lock
flutter/flet_geolocator/pubspec.yaml
flutter/flet_geolocator/lib/flet_geolocator.dart
flutter/flet_geolocator/lib/src/extension.dart
flutter/flet_geolocator/lib/src/geolocator.dart
flutter/flet_geolocator/lib/src/utils/geolocator.dart
flet_geolocator-0.80.5.dist-info/METADATA
flet_geolocator-0.80.5.dist-info/WHEEL
flet_geolocator-0.80.5.dist-info/top_level.txt
flet_geolocator-0.80.5.dist-info/RECORD
